windirs/__init__.py
windirs/windirs.py
windirs-1.1.1.dist-info/DESCRIPTION.rst
windirs-1.1.1.dist-info/METADATA
windirs-1.1.1.dist-info/RECORD
windirs-1.1.1.dist-info/WHEEL
windirs-1.1.1.dist-info/metadata.json
windirs-1.1.1.dist-info/top_level.txt
