Metadata-Version: 2.0
Name: windirs
Version: 1.1.1
Summary: Windows path wrapper
Home-page: UNKNOWN
Author: Isaac Robinson
Author-email: isaac@rirobinson.com
License: UNKNOWN
Platform: UNKNOWN
